awscdk/appsync_utils/__init__.py
awscdk/appsync_utils/py.typed
awscdk/appsync_utils/_jsii/__init__.py
awscdk/appsync_utils/_jsii/awscdk-appsync-utils@0.0.858.jsii.tgz
cdklabs_appsync_utils-0.0.858.dist-info/LICENSE
cdklabs_appsync_utils-0.0.858.dist-info/METADATA
cdklabs_appsync_utils-0.0.858.dist-info/NOTICE
cdklabs_appsync_utils-0.0.858.dist-info/WHEEL
cdklabs_appsync_utils-0.0.858.dist-info/top_level.txt
cdklabs_appsync_utils-0.0.858.dist-info/RECORD
